slushie/__init__.py
slushie/main.py
tests/__init__.py
tests/test_main.py
slushie-0.2.4.dist-info/LICENSE
slushie-0.2.4.dist-info/METADATA
slushie-0.2.4.dist-info/WHEEL
slushie-0.2.4.dist-info/top_level.txt
slushie-0.2.4.dist-info/RECORD
