Metadata-Version: 2.1
Name: slushie
Version: 0.2.4
Summary: Slushie: A Python library for relative path manipulation.
Home-page: https://github.com/saleguas/slushie
Author: Salvador Aleguas
Author-email: salvadoraleguas@example.com
License: MIT
Keywords: path sys-path manipulation python-path module-path
Platform: UNKNOWN
Classifier: Development Status :: 3 - Alpha
Classifier: Intended Audience :: Developers
Classifier: License :: OSI Approved :: MIT License
Classifier: Programming Language :: Python :: 3
Classifier: Programming Language :: Python :: 3.12
Requires-Python: >=3
License-File: LICENSE
